pymake/__init__.py
pymake/bare.py
pymake/cmake.py
mypymake-0.1.5.dist-info/LICENSE
mypymake-0.1.5.dist-info/METADATA
mypymake-0.1.5.dist-info/WHEEL
mypymake-0.1.5.dist-info/top_level.txt
mypymake-0.1.5.dist-info/RECORD
