Metadata-Version: 2.1
Name: mypymake
Version: 0.1.5
Summary: PyMake is a simple, Python-based build system designed to simplify the process of compiling and running C++ projects. It provides an intuitive API for configuring your build process and executing compiled programs.
Author-email: me <superdeveloper43@gmail.com>
License: The MIT License (MIT)
Project-URL: Home, https://github.com/fresh-milkshake/pymake
Classifier: License :: OSI Approved :: MIT License
Requires-Python: >=3.10
License-File: LICENSE
